{
  "zones": {
    "https://trouverunlogement.lescrous.fr/tools/47/search?bounds=3.1311025_50.6150217_3.1514338_50.6030654&locationName=Cit%C3%A9+Scientifique+-+Lille1%2C+Villeneuve-d%27Ascq": {
      "available": [],
      "errors": 0
    },
    "https://trouverunlogement.lescrous.fr/tools/47/search?bounds=2.9679677_50.6612596_3.125725_50.6008264&locationName=Lille": {
      "available": [],
      "errors": 0
    },
    "https://trouverunlogement.lescrous.fr/tools/47/search?bounds=3.1158064_50.6732934_3.2078132_50.5985301&locationName=Villeneuve-d%27Ascq": {
      "available": [],
      "errors": 0
    }
  },
  "last_heartbeat": "2026-07-07"
}